karlovic/.gitignore
karlovic/__init__.py
karlovic/api.py
karlovic/basic_authorization.py
karlovic/execution_time.py
karlovic/forms/__init__.py
karlovic/forms/use_image_form.py
karlovic/middleware.py
karlovic/model_server.py
karlovic/plugins/__init__.py
karlovic/plugins/cuda_device_plugin.py
karlovic/plugins/ensure_nonconflicting_plugins.py
karlovic/plugins/get_plugin_value.py
karlovic/plugins/image_plugin.py
karlovic/plugins/image_to_features_plugin.py
karlovic/request_logger.py
karlovic-0.1.4b0.dist-info/LICENSE
karlovic-0.1.4b0.dist-info/WHEEL
karlovic-0.1.4b0.dist-info/METADATA
karlovic-0.1.4b0.dist-info/RECORD
